setup.py
distributions_gaussian_binomial/Binomialdistribution.py
distributions_gaussian_binomial/Gaussiandistribution.py
distributions_gaussian_binomial/Generaldistribution.py
distributions_gaussian_binomial/__init__.py
distributions_gaussian_binomial.egg-info/PKG-INFO
distributions_gaussian_binomial.egg-info/SOURCES.txt
distributions_gaussian_binomial.egg-info/dependency_links.txt
distributions_gaussian_binomial.egg-info/not-zip-safe
distributions_gaussian_binomial.egg-info/top_level.txt